setup.py
blns/__init__.py
blns/blns.py
blns.egg-info/PKG-INFO
blns.egg-info/SOURCES.txt
blns.egg-info/dependency_links.txt
blns.egg-info/top_level.txt