Metadata-Version: 1.0
Name: blns
Version: 0.1.7
Summary: Big List of Naughty String. Forked from https://github.com/minimaxir/big-list-of-naughty-strings
Home-page: https://github.com/danggrianto/big-list-of-naughty-strings
Author: Daniel Anggrianto
Author-email: daniel@anggrianto.com
License: MIT
Keywords: Big List of Naughty String
Platform: any
